shayancalculatortest/__init__.py
shayancalculatortest/api_helper.py
shayancalculatortest/configuration.py
shayancalculatortest/decorators.py
shayancalculatortest/shayancalculatortest_client.py
shayancalculatortest/controllers/__init__.py
shayancalculatortest/controllers/base_controller.py
shayancalculatortest/controllers/simple_calculator_controller.py
shayancalculatortest/exceptions/__init__.py
shayancalculatortest/exceptions/api_exception.py
shayancalculatortest/http/__init__.py
shayancalculatortest/http/http_call_back.py
shayancalculatortest/http/http_client.py
shayancalculatortest/http/http_context.py
shayancalculatortest/http/http_method_enum.py
shayancalculatortest/http/http_request.py
shayancalculatortest/http/http_response.py
shayancalculatortest/http/requests_client.py
shayancalculatortest/models/__init__.py
shayancalculatortest/models/operation_type_enum.py
tests/__init__.py
tests/http_response_catcher.py
tests/test_helper.py
tests/controllers/__init__.py
tests/controllers/controller_test_base.py
tests/controllers/test_simple_calculator_controller.py
shayancalculatortest-1.0.0.dist-info/LICENSE
shayancalculatortest-1.0.0.dist-info/METADATA
shayancalculatortest-1.0.0.dist-info/WHEEL
shayancalculatortest-1.0.0.dist-info/top_level.txt
shayancalculatortest-1.0.0.dist-info/RECORD
